{
  "graphql": { "name": "GraphQL", "parent": "javascript" },
  "reactnative": { "name": "React Native", "parent": "javascript" },
  "pdfjs": { "name": "pdf.js", "parent": "javascript" },
  "tesseractjs": { "name": "Tesseract.js", "parent": "javascript" },
  "d3js": { "name": "d3.js", "parent": "javascript" },
  "threejs": { "name": "three.js", "parent": "javascript" },
  "angularjs": { "name": "Angular.js", "parent": "javascript" },
  "antdesign": { "name": "Ant Design", "parent": "javascript" },
  "backbonejs": { "name": "Backbone.js", "parent": "javascript" },
  "bootstrap": { "name": "Bootstrap", "parent": "javascript" },
  "cheeriojs": { "name": "Cheerio.js", "parent": "javascript" },
  "emberjs": { "name": "Ember.js", "parent": "javascript" },
  "expressjs": { "name": "Express", "parent": "javascript" },
  "fastifyjs": { "name": "Fastify", "parent": "javascript" },
  "handlebars": { "name": "Handlebars", "parent": "javascript" },
  "jquery": { "name": "jQuery", "parent": "javascript" },
  "jqueryui": { "name": "jQuery UI", "parent": "javascript" },
  "knockoutjs": { "name": "Knockout.js", "parent": "javascript" },
  "koa": { "name": "Koa", "parent": "javascript" },
  "meteor": { "name": "Meteor", "parent": "javascript" },
  "gpujs": { "name": "GPU.js", "parent": "javascript" },
  "sharejs": { "name": "Share.js", "parent": "javascript" },
  "quasarjs": { "name": "Quasar", "parent": "javascript" },
  "materialui": { "name": "Material UI", "parent": "javascript" },
  "mustache": { "name": "Mustache.js", "parent": "javascript" },
  "pug": { "name": "Pug", "parent": "javascript" },
  "react": { "name": "React", "parent": "javascript" },
  "preact": { "name": "PReact", "parent": "javascript" },
  "passportjs": { "name": "Passport.js", "parent": "javascript" },
  "p5js": { "name": "p5.js", "parent": "javascript" },
  "redux": { "name": "Redux", "parent": "javascript" },
  "riot": { "name": "Riot.js", "parent": "javascript" },
  "rxjslite": { "name": "RxJS Lite", "parent": "javascript" },
  "socketio": { "name": "Socket.io", "parent": "javascript" },
  "svelte": { "name": "Svelte", "parent": "javascript", "color": "#ff3302" },
  "vuex": { "name": "Vuex", "parent": "javascript" },
  "nuxtjs": { "name": "Nuxt.js", "parent": "vue" },
  "ml5": { "name": "ML5.js", "parent": "javascript" },
  "webpack": { "name": "Webpack", "parent": "javascript" },
  "knexjs": { "name": "Knex.js", "parent": "javascript" },
  "bookshelfjs": { "name": "Bookshelf.js", "parent": "javascript" },
  "lodashjs": { "name": "lodash.js", "parent": "javascript" },
  "momentjs": { "name": "moment.js", "parent": "javascript" },
  "sequelizejs": { "name": "Sequelize.js", "parent": "javascript" },
  "mongoosejs": { "name": "Mongoose.js", "parent": "javascript" },
  "mobx": { "name": "Mobx", "parent": "javascript" },
  "webcomponents": { "name": "Web Components", "parent": "javascript" },
  "racerjs": { "name": "Racer.js", "parent": "javascript" },
  "nodejs": { "name": "Node.js", "color": "#619D67" }
}
